daytona_openai_demo.py
daytona_openai_demo-0.1.1.dist-info/licenses/LICENSE
daytona_openai_demo-0.1.1.dist-info/METADATA
daytona_openai_demo-0.1.1.dist-info/WHEEL
daytona_openai_demo-0.1.1.dist-info/top_level.txt
daytona_openai_demo-0.1.1.dist-info/RECORD
