Metadata-Version: 2.4
Name: daytona-openai-demo
Version: 0.1.1
Summary: Enhanced OpenAI client with Daytona sandbox execution capabilities
Home-page: https://github.com/brunogrbavac/daytona-openai
Author: Bruno Grbavac
Author-email: Bruno Grbavac <info@daytona.io>
License: MIT
Project-URL: Homepage, https://github.com/brunogrbavac/daytona-openai
Project-URL: Issues, https://github.com/brunogrbavac/daytona-openai/issues
Project-URL: Documentation, https://github.com/brunogrbavac/daytona-openai#readme
Keywords: openai,daytona,ai,compute,sandbox
Classifier: Development Status :: 3 - Alpha
Classifier: Intended Audience :: Developers
Classifier: License :: OSI Approved :: MIT License
Classifier: Programming Language :: Python :: 3
Classifier: Programming Language :: Python :: 3.10
Classifier: Programming Language :: Python :: 3.11
Classifier: Programming Language :: Python :: 3.12
Requires-Python: >=3.10
License-File: LICENSE
Requires-Dist: openai>=1.0.0
Requires-Dist: daytona-sdk
Dynamic: author
Dynamic: home-page
Dynamic: license-file
Dynamic: requires-python
